tourneyket/__init__.py
tourneyket/__main__.py
tourneyket-1.0.1.dist-info/METADATA
tourneyket-1.0.1.dist-info/WHEEL
tourneyket-1.0.1.dist-info/licenses/LICENSE
tourneyket-1.0.1.dist-info/RECORD
