Metadata-Version: 2.4
Name: Tourneyket
Version: 1.0.1
Summary: Easily represent, progress, and visualize Bracket-style Tournaments
Project-URL: Homepage, https://github.com/shoenot/tourneyket
Project-URL: Issues, https://github.com/shoenot/tourneyket/issues
Author-email: Shurjo Sakib Masood <mail@shurjo.me>
License-Expression: MIT
License-File: LICENSE
Classifier: Operating System :: OS Independent
Classifier: Programming Language :: Python :: 3
Requires-Python: >=3.9
